{
    "http-content-length": 33375681,
    "http-etag": null,
    "http-last-modified": "Fri, 07 Apr 2023 07:35:51 GMT",
    "http-last-modified-float": 1680824151.0,
    "http-content-type": "audio/mpeg",
    "http-content-disposition-raw": null,
    "http-content-disposition-filename": null,
    "actual-size": 33375681,
    "actual-duration": 2763,
    "sha1": "42b0e19213b30102cf5e7a72fde379abfda3664f",
    "md5": "c54308a700f4887d0d90e834221b38c1",
    "url-history": {
        "0": {
            "status_code": 302,
            "url": "https://aphid.fireside.fm/d/1437767933/8ecd4d04-d9eb-48ed-bafc-9ab55e67c940/771e7f69-1637-46b3-8e0f-cd89ec6ad390.mp3",
            "headers": {
                "server": "nginx",
                "date": "Fri, 07 Apr 2023 07:35:50 GMT",
                "content-type": "text/html; charset=utf-8",
                "transfer-encoding": "chunked",
                "x-frame-options": "SAMEORIGIN",
                "x-xss-protection": "1; mode=block",
                "x-content-type-options": "nosniff",
                "x-download-options": "noopen",
                "x-permitted-cross-domain-policies": "none",
                "referrer-policy": "strict-origin-when-cross-origin",
                "access-control-allow-origin": "*",
                "access-control-allow-methods": "GET",
                "access-control-request-method": "*",
                "access-control-allow-headers": "Origin, X-Requested-With, Content-Type, Accept, Authorization",
                "location": "https://media.fireside.fm/file/fireside-audio/podcasts/audio/8/8ecd4d04-d9eb-48ed-bafc-9ab55e67c940/episodes/7/771e7f69-1637-46b3-8e0f-cd89ec6ad390/771e7f69-1637-46b3-8e0f-cd89ec6ad390.mp3",
                "cache-control": "no-cache",
                "x-request-id": "cb513753-6779-4754-8ca8-6ee8429cb7b2",
                "x-runtime": "0.006291",
                "x-backend-server": "web02.fireside.fm",
                "x-served-by": "Fireside",
                "connection": "close"
            }
        },
        "1": {
            "status_code": 200,
            "url": "https://media.fireside.fm/file/fireside-audio/podcasts/audio/8/8ecd4d04-d9eb-48ed-bafc-9ab55e67c940/episodes/7/771e7f69-1637-46b3-8e0f-cd89ec6ad390/771e7f69-1637-46b3-8e0f-cd89ec6ad390.mp3",
            "headers": {
                "Date": "Fri, 07 Apr 2023 07:35:51 GMT",
                "Content-Type": "audio/mpeg",
                "Content-Length": "33375681",
                "Connection": "keep-alive",
                "x-bz-file-name": "podcasts/audio/8/8ecd4d04-d9eb-48ed-bafc-9ab55e67c940/episodes/7/771e7f69-1637-46b3-8e0f-cd89ec6ad390/771e7f69-1637-46b3-8e0f-cd89ec6ad390.mp3",
                "x-bz-file-id": "4_z125a778b4015af03668a081e_f118378f8f0a0b06c_d20200720_m082150_c001_v0001136_t0048",
                "x-bz-content-sha1": "42b0e19213b30102cf5e7a72fde379abfda3664f",
                "X-Bz-Upload-Timestamp": "1595233310000",
                "Cache-Control": "max-age=604800",
                "Last-Modified": "Fri, 07 Apr 2023 07:35:51 GMT",
                "CF-Cache-Status": "MISS",
                "Accept-Ranges": "bytes",
                "Vary": "Accept-Encoding",
                "Server": "cloudflare",
                "CF-RAY": "7b40989c89f91b0a-PHX"
            }
        }
    }
}