{
    "title": "#97 这个世界对科研人员有多难",
    "title_detail": {
        "type": "text/plain",
        "language": null,
        "base": "https://feeds.fireside.fm/shengdongjixi/rss",
        "value": "#97 这个世界对科研人员有多难"
    },
    "links": [
        {
            "rel": "alternate",
            "type": "text/html",
            "href": "http://etw.fm/phd-researchers"
        },
        {
            "length": "55905303",
            "type": "audio/mpeg",
            "href": "https://chtbl.com/track/GGD9D/aphid.fireside.fm/d/1437767933/8dd8a56f-9636-415a-8c00-f9ca6778e511/40c3e6a5-626b-44d4-9470-e2304f16ef9e.mp3",
            "rel": "enclosure"
        }
    ],
    "link": "http://etw.fm/phd-researchers",
    "id": "40c3e6a5-626b-44d4-9470-e2304f16ef9e",
    "guidislink": false,
    "published": "Thu, 14 Nov 2019 11:00:00 +0800",
    "published_parsed": [
        2019,
        11,
        14,
        3,
        0,
        0,
        3,
        318,
        0
    ],
    "authors": [
        {
            "name": "ETW Studio"
        },
        {
            "name": "ETW Studio"
        }
    ],
    "author": "ETW Studio",
    "author_detail": {
        "name": "ETW Studio"
    },
    "itunes_episodetype": "full",
    "subtitle": "",
    "subtitle_detail": {
        "type": "text/plain",
        "language": null,
        "base": "https://feeds.fireside.fm/shengdongjixi/rss",
        "value": ""
    },
    "itunes_duration": "58:13",
    "itunes_explicit": null,
    "summary": "<p><strong>主播丨</strong> 徐涛</p>\n\n<p><strong>嘉宾丨</strong> 李文勤，薛渊</p>\n\n<p><strong>后期制作丨</strong> 迪卡普里鑫</p>\n\n<p>能做科研人员，在大学/科研机构里做研究，曾被认为是完美工作：受人尊敬，还能享受寒暑假。</p>\n\n<p>可现实情况也许已经改变：长期没有科研成就的挫败感，超长工作时间，职业发展的不安全感，社会的浮躁以及周围人的期待，都给科研人员带来了身体上和心灵上的双重压力。</p>\n\n<p>本期节目的嘉宾正是两位科研人员，他们有着在美国和中国两地做科研的经验。我们在这期节目里，探讨这些压力背后更深层原因，也因此更了解现代科研系统的运作。</p>\n\n<p>当然，我们也希望大家，尤其是从事科研的听众听了本期节目后，能够正确看待身上的压力并平衡好生活。</p>\n\n<p>另外，<strong>「声动活泼」正在筹划一档新的播客节目 ——「反潮流俱乐部」</strong>。在这档节目里，我们会涉足时尚和潮流圈，并展示背后有趣、深刻的那一面，我们正在向全球征集支持者，如果你感兴趣，<strong>可以在下面三个众筹平台上支持我们，并能解锁收听第一期的demo，同时获得相应的权益。</strong></p>\n\n<p>国内支持→<a href=\"https://www.chongya.com/@shengfm\" rel=\"nofollow\">「冲呀 」</a></p>\n\n<p>国内支持→<a href=\"https://afdian.net/@shengfm\" rel=\"nofollow\">「爱发电」</a></p>\n\n<p>国外支持→<a href=\"https://www.patreon.com/shengfm\" rel=\"nofollow\">「patreon」</a></p>\n\n<p><strong>嘉宾简介</strong><br />\n李文勤，美国Lawrence Livermore National Lab 研究员<br />\n薛渊，中国上海交通大学，助理教授</p>\n\n<p><strong>Enjoy!</strong></p>\n\n<p><strong>BGM</strong><br />\n1  Book Bag-E's Jammy Jams<br />\n2  On Our Merry Way-Dylan Sitts</p><p>Special Guests: 李文勤 and 薛渊.</p>",
    "summary_detail": {
        "type": "text/html",
        "language": null,
        "base": "https://feeds.fireside.fm/shengdongjixi/rss",
        "value": "<p><strong>主播丨</strong> 徐涛</p>\n\n<p><strong>嘉宾丨</strong> 李文勤，薛渊</p>\n\n<p><strong>后期制作丨</strong> 迪卡普里鑫</p>\n\n<p>能做科研人员，在大学/科研机构里做研究，曾被认为是完美工作：受人尊敬，还能享受寒暑假。</p>\n\n<p>可现实情况也许已经改变：长期没有科研成就的挫败感，超长工作时间，职业发展的不安全感，社会的浮躁以及周围人的期待，都给科研人员带来了身体上和心灵上的双重压力。</p>\n\n<p>本期节目的嘉宾正是两位科研人员，他们有着在美国和中国两地做科研的经验。我们在这期节目里，探讨这些压力背后更深层原因，也因此更了解现代科研系统的运作。</p>\n\n<p>当然，我们也希望大家，尤其是从事科研的听众听了本期节目后，能够正确看待身上的压力并平衡好生活。</p>\n\n<p>另外，<strong>「声动活泼」正在筹划一档新的播客节目 ——「反潮流俱乐部」</strong>。在这档节目里，我们会涉足时尚和潮流圈，并展示背后有趣、深刻的那一面，我们正在向全球征集支持者，如果你感兴趣，<strong>可以在下面三个众筹平台上支持我们，并能解锁收听第一期的demo，同时获得相应的权益。</strong></p>\n\n<p>国内支持→<a href=\"https://www.chongya.com/@shengfm\" rel=\"nofollow\">「冲呀 」</a></p>\n\n<p>国内支持→<a href=\"https://afdian.net/@shengfm\" rel=\"nofollow\">「爱发电」</a></p>\n\n<p>国外支持→<a href=\"https://www.patreon.com/shengfm\" rel=\"nofollow\">「patreon」</a></p>\n\n<p><strong>嘉宾简介</strong><br />\n李文勤，美国Lawrence Livermore National Lab 研究员<br />\n薛渊，中国上海交通大学，助理教授</p>\n\n<p><strong>Enjoy!</strong></p>\n\n<p><strong>BGM</strong><br />\n1  Book Bag-E's Jammy Jams<br />\n2  On Our Merry Way-Dylan Sitts</p><p>Special Guests: 李文勤 and 薛渊.</p>"
    },
    "tags": [
        {
            "term": "科研",
            "scheme": "http://www.itunes.com/",
            "label": null
        },
        {
            "term": "压力",
            "scheme": "http://www.itunes.com/",
            "label": null
        },
        {
            "term": "博士",
            "scheme": "http://www.itunes.com/",
            "label": null
        },
        {
            "term": "大学教师",
            "scheme": "http://www.itunes.com/",
            "label": null
        },
        {
            "term": "研究",
            "scheme": "http://www.itunes.com/",
            "label": null
        },
        {
            "term": "科研人员",
            "scheme": "http://www.itunes.com/",
            "label": null
        },
        {
            "term": "访谈",
            "scheme": "http://www.itunes.com/",
            "label": null
        },
        {
            "term": "播客",
            "scheme": "http://www.itunes.com/",
            "label": null
        }
    ],
    "content": [
        {
            "type": "text/html",
            "language": null,
            "base": "https://feeds.fireside.fm/shengdongjixi/rss",
            "value": "<p><strong>主播丨</strong> 徐涛</p>\n\n<p><strong>嘉宾丨</strong> 李文勤，薛渊</p>\n\n<p><strong>后期制作丨</strong> 迪卡普里鑫</p>\n\n<p>能做科研人员，在大学/科研机构里做研究，曾被认为是完美工作：受人尊敬，还能享受寒暑假。</p>\n\n<p>可现实情况也许已经改变：长期没有科研成就的挫败感，超长工作时间，职业发展的不安全感，社会的浮躁以及周围人的期待，都给科研人员带来了身体上和心灵上的双重压力。</p>\n\n<p>本期节目的嘉宾正是两位科研人员，他们有着在美国和中国两地做科研的经验。我们在这期节目里，探讨这些压力背后更深层原因，也因此更了解现代科研系统的运作。</p>\n\n<p>当然，我们也希望大家，尤其是从事科研的听众听了本期节目后，能够正确看待身上的压力并平衡好生活。</p>\n\n<p>另外，<strong>「声动活泼」正在筹划一档新的播客节目 ——「反潮流俱乐部」</strong>。在这档节目里，我们会涉足时尚和潮流圈，并展示背后有趣、深刻的那一面，我们正在向全球征集支持者，如果你感兴趣，<strong>可以在下面三个众筹平台上支持我们，并能解锁收听第一期的demo，同时获得相应的权益。</strong></p>\n\n<p>国内支持→<a href=\"https://www.chongya.com/@shengfm\" rel=\"nofollow\">「冲呀 」</a></p>\n\n<p>国内支持→<a href=\"https://afdian.net/@shengfm\" rel=\"nofollow\">「爱发电」</a></p>\n\n<p>国外支持→<a href=\"https://www.patreon.com/shengfm\" rel=\"nofollow\">「patreon」</a></p>\n\n<p><strong>嘉宾简介</strong><br />\n李文勤，美国Lawrence Livermore National Lab 研究员<br />\n薛渊，中国上海交通大学，助理教授</p>\n\n<p><strong>Enjoy!</strong></p>\n\n<p><strong>BGM</strong><br />\n1  Book Bag-E's Jammy Jams<br />\n2  On Our Merry Way-Dylan Sitts</p><p>Special Guests: 李文勤 and 薛渊.</p>"
        }
    ],
    "fireside_playerurl": "https://fireside.fm/player/v2/zS8AJ4Mi+CVT1wZdJ",
    "fireside_playerembedcode": "<iframe src=\"https://fireside.fm/player/v2/zS8AJ4Mi+CVT1wZdJ\" width=\"740\" height=\"200\" frameborder=\"0\" scrolling=\"no\">",
    "podcast_person": {
        "email": "",
        "href": "",
        "role": "guest"
    }
}