{
    "links": [
        {
            "length": "80608010",
            "type": "audio/mpeg",
            "href": "https://r.typlog.com/eyJzIjoxNTI4LCJlIjo0MDAzLCJwIjoyLCJ1IjoiN2Q4ZC5tcDMifQ.W3RNurS0UQv4OhkAX3ASfpfdBqg/bowuzhi/z_c05ecb9520a188e7bfcfac698e4c7d8d.mp3",
            "rel": "enclosure"
        },
        {
            "rel": "alternate",
            "type": "text/html",
            "href": "http://bowuzhi.fm/episodes/20"
        }
    ],
    "title": "#20: 伊朗旅游局委派制作之特别节目",
    "title_detail": {
        "type": "text/plain",
        "language": null,
        "base": "http://bowuzhi.fm/feed/audio.xml",
        "value": "#20: 伊朗旅游局委派制作之特别节目"
    },
    "id": "http://bowuzhi.fm/episodes/20",
    "guidislink": true,
    "link": "http://bowuzhi.fm/episodes/20",
    "authors": [
        {
            "name": "bowuzhi"
        }
    ],
    "author": "bowuzhi",
    "author_detail": {
        "name": "bowuzhi"
    },
    "itunes_duration": "1:51:48",
    "itunes_explicit": null,
    "itunes_episodetype": "None",
    "summary": "&lt;p&gt;《紫禁城》杂志的任超先生又回来了，带来的话题是伊朗：一个填补知识空白、颠覆既定印象、增长（cháng）旅游目的地清单的话题。&lt;/p&gt; 章节（时:分:秒）： 00:00:00 开场 00:00:36 任超先生的伊朗之行 00:23:00 关于伊斯兰教的建筑、装饰和传统等 00:44:25 青花瓷与伊朗 00:58:43 波斯波利斯、文化之间的相互影响 01:13:45 伊朗世俗化的失败 01:32:34 旅游纪念品购物指南（伪） 01:36:20 伊朗博物馆推荐 01:42:00 伊朗能喝酒吗？ 01:46:50 尾声：伊朗旅游宣传及闲聊 《博物志》网站：http://bowuzhi.fm 如果您喜欢《博物志》，请考虑成为《博物志》的会员支持婉莹和大黄。会员有机会收到购自世界各地博物馆的精美礼品：http://bowuzhi.fm/member 我们推荐您使用泛用型播客客户端订阅收听《博物志》，但您也可以在喜马拉雅、荔枝 FM 或网易云音乐收听。 相关链接 琐罗亚斯德教 沙利亚法 居鲁士文书 美军士兵在硫磺岛竖起国旗 波斯波利斯 唤礼 西安化觉巷大清真寺 居鲁士二世 伊朗国家博物馆 礼撒阿巴斯博物馆 伊朗玻璃和陶瓷博物馆 人物简介 婉莹：新鲜毕业的博物馆学硕士 任超：《紫禁城》杂志编辑Support 博物志",
    "summary_detail": {
        "type": "text/html",
        "language": null,
        "base": "http://bowuzhi.fm/feed/audio.xml",
        "value": "&lt;p&gt;《紫禁城》杂志的任超先生又回来了，带来的话题是伊朗：一个填补知识空白、颠覆既定印象、增长（cháng）旅游目的地清单的话题。&lt;/p&gt; 章节（时:分:秒）： 00:00:00 开场 00:00:36 任超先生的伊朗之行 00:23:00 关于伊斯兰教的建筑、装饰和传统等 00:44:25 青花瓷与伊朗 00:58:43 波斯波利斯、文化之间的相互影响 01:13:45 伊朗世俗化的失败 01:32:34 旅游纪念品购物指南（伪） 01:36:20 伊朗博物馆推荐 01:42:00 伊朗能喝酒吗？ 01:46:50 尾声：伊朗旅游宣传及闲聊 《博物志》网站：http://bowuzhi.fm 如果您喜欢《博物志》，请考虑成为《博物志》的会员支持婉莹和大黄。会员有机会收到购自世界各地博物馆的精美礼品：http://bowuzhi.fm/member 我们推荐您使用泛用型播客客户端订阅收听《博物志》，但您也可以在喜马拉雅、荔枝 FM 或网易云音乐收听。 相关链接 琐罗亚斯德教 沙利亚法 居鲁士文书 美军士兵在硫磺岛竖起国旗 波斯波利斯 唤礼 西安化觉巷大清真寺 居鲁士二世 伊朗国家博物馆 礼撒阿巴斯博物馆 伊朗玻璃和陶瓷博物馆 人物简介 婉莹：新鲜毕业的博物馆学硕士 任超：《紫禁城》杂志编辑Support 博物志"
    },
    "content": [
        {
            "type": "text/html",
            "language": null,
            "base": "http://bowuzhi.fm/feed/audio.xml",
            "value": "<pre><code>            &lt;p&gt;《紫禁城》杂志的任超先生又回来了，带来的话题是伊朗：一个填补知识空白、颠覆既定印象、增长（cháng）旅游目的地清单的话题。&lt;/p&gt;\n</code></pre>\n\n<p>章节（时:分:秒）：</p>\n\n<p>00:00:00 开场<br />\n00:00:36 任超先生的伊朗之行<br />\n00:23:00 关于伊斯兰教的建筑、装饰和传统等<br />\n00:44:25 青花瓷与伊朗<br />\n00:58:43 波斯波利斯、文化之间的相互影响<br />\n01:13:45 伊朗世俗化的失败<br />\n01:32:34 旅游纪念品购物指南（伪）<br />\n01:36:20 伊朗博物馆推荐<br />\n01:42:00 伊朗能喝酒吗？<br />\n01:46:50 尾声：伊朗旅游宣传及闲聊</p>\n\n<p>《博物志》网站：<a href=\"http://bowuzhi.fm\">http://bowuzhi.fm</a></p>\n\n<p>如果您喜欢《博物志》，请考虑成为《博物志》的会员支持婉莹和大黄。会员有机会收到购自世界各地博物馆的精美礼品：<a href=\"http://bowuzhi.fm/member\">http://bowuzhi.fm/member</a></p>\n\n<p>我们推荐您使用<a href=\"https://ipn.li/faq\">泛用型播客客户端</a>订阅收听《博物志》，但您也可以在<a href=\"http://www.ximalaya.com/#/23682075/album/2933689\">喜马拉雅</a>、<a href=\"http://www.lizhi.fm/1821570/\">荔枝 FM</a> 或<a href=\"http://music.163.com/#/djradio?id=3532007\">网易云音乐</a>收听。</p>\n\n<h2>相关链接</h2>\n\n<ul>\n<li><a href=\"https://zh.wikipedia.org/wiki/%E7%90%90%E7%BD%97%E4%BA%9A%E6%96%AF%E5%BE%B7%E6%95%99\">琐罗亚斯德教</a></li>\n<li><a href=\"https://zh.wikipedia.org/zh/%E4%BC%8A%E6%96%AF%E8%98%AD%E6%95%99%E6%B3%95\">沙利亚法</a></li>\n<li><a href=\"https://zh.wikipedia.org/zh/%E5%B1%85%E9%AD%AF%E5%A3%AB%E6%96%87%E6%9B%B8\">居鲁士文书</a></li>\n<li><a href=\"https://zh.wikipedia.org/wiki/美軍士兵在硫磺島豎起國旗\">美军士兵在硫磺岛竖起国旗</a></li>\n<li><a href=\"https://zh.wikipedia.org/wiki/%E6%B3%A2%E6%96%AF%E6%B3%A2%E5%88%A9%E6%96%AF\">波斯波利斯</a></li>\n<li><a href=\"https://en.wikipedia.org/wiki/Azan\">唤礼</a></li>\n<li><a href=\"https://en.wikipedia.org/wiki/Azan\">西安化觉巷大清真寺</a></li>\n<li><a href=\"https://zh.wikipedia.org/wiki/%E5%B1%85%E9%B2%81%E5%A3%AB%E4%BA%8C%E4%B8%96\">居鲁士二世</a></li>\n<li><a href=\"https://en.wikipedia.org/wiki/National_Museum_of_Iran\">伊朗国家博物馆</a></li>\n<li><a href=\"http://www.rezaabbasimuseum.ir/\">礼撒阿巴斯博物馆</a></li>\n<li><a href=\"http://www.glasswaremuseum.ir/\">伊朗玻璃和陶瓷博物馆</a></li>\n</ul>\n\n<h2>人物简介</h2>\n\n<p>婉莹：新鲜毕业的博物馆学硕士<br />\n任超：《紫禁城》杂志编辑</p><p><a href=\"https://bowuzhi.fm/member\" rel=\"payment\">Support 博物志</a></p>"
        },
        {
            "type": "text/html",
            "language": null,
            "base": "http://bowuzhi.fm/feed/audio.xml",
            "value": "<pre><code>            &lt;p&gt;《紫禁城》杂志的任超先生又回来了，带来的话题是伊朗：一个填补知识空白、颠覆既定印象、增长（cháng）旅游目的地清单的话题。&lt;/p&gt;\n</code></pre>\n\n<p>章节（时:分:秒）：</p>\n\n<p>00:00:00 开场<br />\n00:00:36 任超先生的伊朗之行<br />\n00:23:00 关于伊斯兰教的建筑、装饰和传统等<br />\n00:44:25 青花瓷与伊朗<br />\n00:58:43 波斯波利斯、文化之间的相互影响<br />\n01:13:45 伊朗世俗化的失败<br />\n01:32:34 旅游纪念品购物指南（伪）<br />\n01:36:20 伊朗博物馆推荐<br />\n01:42:00 伊朗能喝酒吗？<br />\n01:46:50 尾声：伊朗旅游宣传及闲聊</p>\n\n<p>《博物志》网站：<a href=\"http://bowuzhi.fm\">http://bowuzhi.fm</a></p>\n\n<p>如果您喜欢《博物志》，请考虑成为《博物志》的会员支持婉莹和大黄。会员有机会收到购自世界各地博物馆的精美礼品：<a href=\"http://bowuzhi.fm/member\">http://bowuzhi.fm/member</a></p>\n\n<p>我们推荐您使用<a href=\"https://ipn.li/faq\">泛用型播客客户端</a>订阅收听《博物志》，但您也可以在<a href=\"http://www.ximalaya.com/#/23682075/album/2933689\">喜马拉雅</a>、<a href=\"http://www.lizhi.fm/1821570/\">荔枝 FM</a> 或<a href=\"http://music.163.com/#/djradio?id=3532007\">网易云音乐</a>收听。</p>\n\n<h2>相关链接</h2>\n\n<ul>\n<li><a href=\"https://zh.wikipedia.org/wiki/%E7%90%90%E7%BD%97%E4%BA%9A%E6%96%AF%E5%BE%B7%E6%95%99\">琐罗亚斯德教</a></li>\n<li><a href=\"https://zh.wikipedia.org/zh/%E4%BC%8A%E6%96%AF%E8%98%AD%E6%95%99%E6%B3%95\">沙利亚法</a></li>\n<li><a href=\"https://zh.wikipedia.org/zh/%E5%B1%85%E9%AD%AF%E5%A3%AB%E6%96%87%E6%9B%B8\">居鲁士文书</a></li>\n<li><a href=\"https://zh.wikipedia.org/wiki/美軍士兵在硫磺島豎起國旗\">美军士兵在硫磺岛竖起国旗</a></li>\n<li><a href=\"https://zh.wikipedia.org/wiki/%E6%B3%A2%E6%96%AF%E6%B3%A2%E5%88%A9%E6%96%AF\">波斯波利斯</a></li>\n<li><a href=\"https://en.wikipedia.org/wiki/Azan\">唤礼</a></li>\n<li><a href=\"https://en.wikipedia.org/wiki/Azan\">西安化觉巷大清真寺</a></li>\n<li><a href=\"https://zh.wikipedia.org/wiki/%E5%B1%85%E9%B2%81%E5%A3%AB%E4%BA%8C%E4%B8%96\">居鲁士二世</a></li>\n<li><a href=\"https://en.wikipedia.org/wiki/National_Museum_of_Iran\">伊朗国家博物馆</a></li>\n<li><a href=\"http://www.rezaabbasimuseum.ir/\">礼撒阿巴斯博物馆</a></li>\n<li><a href=\"http://www.glasswaremuseum.ir/\">伊朗玻璃和陶瓷博物馆</a></li>\n</ul>\n\n<h2>人物简介</h2>\n\n<p>婉莹：新鲜毕业的博物馆学硕士<br />\n任超：《紫禁城》杂志编辑</p><p><a href=\"https://bowuzhi.fm/member\" rel=\"payment\">Support 博物志</a></p><hr /><p><a href=\"https://afdian.net/@bowuzhi\" rel=\"payment\">爱发电上赞助</a></p>"
        }
    ],
    "published": "Fri, 18 Dec 2015 02:00:00 +0000",
    "published_parsed": [
        2015,
        12,
        18,
        2,
        0,
        0,
        4,
        352,
        0
    ]
}