{
    "links": [
        {
            "length": "44963671",
            "type": "audio/mpeg",
            "href": "https://r.typlog.com/eyJzIjoxNTI4LCJlIjo5NzY3LCJwIjoyLCJ1IjoiMTEwNS5tcDMifQ.KBkPcPtetETpg1it6i6ecz4bBiM/bowuzhi/8371048584_581105.mp3",
            "rel": "enclosure"
        },
        {
            "rel": "alternate",
            "type": "text/html",
            "href": "http://bowuzhi.fm/episodes/196"
        }
    ],
    "title": "196. 美术馆呀浦东咚咚咚",
    "title_detail": {
        "type": "text/plain",
        "language": null,
        "base": "http://bowuzhi.fm/feed/audio.xml",
        "value": "196. 美术馆呀浦东咚咚咚"
    },
    "id": "http://bowuzhi.fm/episodes/196",
    "guidislink": true,
    "link": "http://bowuzhi.fm/episodes/196",
    "authors": [
        {
            "name": "小黄鱼播客"
        }
    ],
    "author": "小黄鱼播客",
    "author_detail": {
        "name": "小黄鱼播客"
    },
    "subtitle": "祝我生日快乐",
    "subtitle_detail": {
        "type": "text/plain",
        "language": null,
        "base": "http://bowuzhi.fm/feed/audio.xml",
        "value": "祝我生日快乐"
    },
    "itunes_duration": "1:30:06",
    "itunes_explicit": true,
    "itunes_episodetype": "None",
    "image": {
        "href": "https://i.typlog.com/bowuzhi/8371048592_038841.jpg?x-oss-process=style/sl"
    },
    "summary": "祝我六岁生日快乐！明年就要上小学了，惆怅。（划掉 感谢 Justpod 借录音室给我们。感谢里林收留婉莹住在家里。 本期节目又名：《我们终于有了理由去浦东！》《Just 浦东，just 噗通》《抽屉原则在博物馆观展之应用》。 登场人物 婉莹：饿得快 btr：抽屉原则研究员 小施：热心市民，消息灵通 延伸链接 八月十五号（明晚）的直播闲聊 井户端会议 B 面电台 浦东美术馆购票入口 巴黎阿拉伯世界文化中心（Institute du Monde Arabe）让·努维尔 卡塔尔国家博物馆 让·努维尔工作室 至上主义 山东白麻石 外滩美术馆第一展：农民达芬奇 《莫失莫忘》石黑一雄 《红发女人》帕慕克 谷歌艺术上的高清 Ophelia 喜欢《博物志》，请考虑成为会员支持我们。 《博物志》的爱发电页面 单独购买往期通讯 购买周边请看这里 Spotify：博物志 Youtube 频道：博物志museelogue Bilibili 频道：博物志 Bilibili 直播间 婉莹的个人电报频道 婉莹的个人YouTube 婉莹的个人哔哩哔哩频道 《哈利播客》公众号",
    "summary_detail": {
        "type": "text/html",
        "language": null,
        "base": "http://bowuzhi.fm/feed/audio.xml",
        "value": "祝我六岁生日快乐！明年就要上小学了，惆怅。（划掉 感谢 Justpod 借录音室给我们。感谢里林收留婉莹住在家里。 本期节目又名：《我们终于有了理由去浦东！》《Just 浦东，just 噗通》《抽屉原则在博物馆观展之应用》。 登场人物 婉莹：饿得快 btr：抽屉原则研究员 小施：热心市民，消息灵通 延伸链接 八月十五号（明晚）的直播闲聊 井户端会议 B 面电台 浦东美术馆购票入口 巴黎阿拉伯世界文化中心（Institute du Monde Arabe）让·努维尔 卡塔尔国家博物馆 让·努维尔工作室 至上主义 山东白麻石 外滩美术馆第一展：农民达芬奇 《莫失莫忘》石黑一雄 《红发女人》帕慕克 谷歌艺术上的高清 Ophelia 喜欢《博物志》，请考虑成为会员支持我们。 《博物志》的爱发电页面 单独购买往期通讯 购买周边请看这里 Spotify：博物志 Youtube 频道：博物志museelogue Bilibili 频道：博物志 Bilibili 直播间 婉莹的个人电报频道 婉莹的个人YouTube 婉莹的个人哔哩哔哩频道 《哈利播客》公众号"
    },
    "content": [
        {
            "type": "text/html",
            "language": null,
            "base": "http://bowuzhi.fm/feed/audio.xml",
            "value": "<p>祝我六岁生日快乐！明年就要上小学了，惆怅。（划掉</p>\n<p>感谢 Justpod 借录音室给我们。感谢里林收留婉莹住在家里。</p>\n<p>本期节目又名：《我们终于有了理由去浦东！》《Just 浦东，just 噗通》《抽屉原则在博物馆观展之应用》。</p>\n<h2>登场人物</h2>\n<p>婉莹：饿得快</p>\n<p>btr：抽屉原则研究员</p>\n<p>小施：热心市民，消息灵通</p>\n<h2>延伸链接</h2>\n<ul>\n<li><a href=\"https://www.clubhouse.com/event/myl44b9ehttps://www.clubhouse.com/event/myl44b9e\">八月十五号（明晚）的直播闲聊</a></li>\n<li><a href=\"https://podcasts.apple.com/cn/podcast/%E7%94%B3%E5%B1%95%E8%BF%90%E5%8A%A8-%E4%B8%8B-%E6%B5%A6%E4%B8%9C%E7%BE%8E%E6%9C%AF%E9%A6%86%E7%9A%84key-words-%E7%A2%97-%E9%87%8E%E5%BF%83-%E5%85%AC%E5%85%B1%E6%80%A7/id1493417568?i=1000529645615\">井户端会议</a></li>\n<li><a href=\"http://m.ximalaya.com/sound/431563018\">B 面电台</a></li>\n<li><a href=\"https://www.museumofartpd.org.cn/ticketing\">浦东美术馆购票入口</a></li>\n<li><a href=\"http://www.iarch.cn/thread-31877-1-1.html\">巴黎阿拉伯世界文化中心（Institute du Monde Arabe）让·努维尔</a></li>\n<li><a href=\"https://www.archdaily.cn/cn/914266/qia-ta-er-guo-jia-bo-wu-guan-rang-star-nu-wei-er-gong-zuo-shi\">卡塔尔国家博物馆 让·努维尔工作室</a></li>\n<li><a href=\"https://zh.wikipedia.org/wiki/%E8%87%B3%E4%B8%8A%E4%B8%BB%E4%B9%89\">至上主义</a></li>\n<li><a href=\"https://baike.baidu.com/item/%E5%B1%B1%E4%B8%9C%E7%99%BD%E9%BA%BB/8245157\">山东白麻石</a></li>\n<li><a href=\"http://www.rockbundartmuseum.org/cn/exhibition/overview/5d0fwz\">外滩美术馆第一展：农民达芬奇</a></li>\n<li><a href=\"https://book.douban.com/subject/30181685//\">《莫失莫忘》石黑一雄</a></li>\n<li><a href=\"https://book.douban.com/subject/30128189/\">《红发女人》帕慕克</a></li>\n<li><a href=\"https://artsandculture.google.com/asset/ophelia-sir-john-everett-millais/-wGU6cT4JixtPA\">谷歌艺术上的高清 Ophelia</a></li>\n</ul>\n<p>喜欢《博物志》，请考虑成为<a href=\"https://bowuzhi.fm/member\">会员</a>支持我们。</p>\n<p><a href=\"https://afdian.net/@bowuzhi\">《博物志》的爱发电页面</a></p>\n<p><a href=\"https://mianbaoduo.com/user/show/aWealms=\">单独购买往期通讯</a></p>\n<p><a href=\"https://weidian.com/?userid=1253336237&amp;p=iphone&amp;wfr=BuyercopyURL&amp;share_relation=a5eeac280c36c7c2__1\">购买周边请看这里</a></p>\n<p>Spotify：<a href=\"https://open.spotify.com/show/3keO8H1ymbuvV7qn36UmAg\">博物志</a></p>\n<p>Youtube 频道：<a href=\"https://www.youtube.com/feed/subscriptions/UC6mRJmp94jsa8megdfQLV4w\">博物志museelogue</a></p>\n<p>Bilibili 频道：<a href=\"https://space.bilibili.com/105185560?from=search&amp;seid=13635414942186953006\">博物志</a></p>\n<p><a href=\"https://live.bilibili.com/21528642?from=search&amp;seid=15255352836414836974\">Bilibili 直播间</a></p>\n<p>婉莹的个人<a href=\"https://t.me/bibiedit\">电报频道</a></p>\n<p>婉莹的个人<a href=\"https://www.youtube.com/channel/UCxlKo7y0lOIAGc0KF9HhAPA\">YouTube</a></p>\n<p>婉莹的个人<a href=\"https://space.bilibili.com/260972304/dynamic\">哔哩哔哩频道</a></p>\n<p><a href=\"https://mp.weixin.qq.com/mp/profile_ext?action=home&amp;__biz=MzU0Nzk3NDk5Ng==&amp;scene=124&amp;#wechat_redirect\">《哈利播客》公众号</a></p>"
        },
        {
            "type": "text/html",
            "language": null,
            "base": "http://bowuzhi.fm/feed/audio.xml",
            "value": "<p>祝我六岁生日快乐！明年就要上小学了，惆怅。（划掉</p>\n<p>感谢 Justpod 借录音室给我们。感谢里林收留婉莹住在家里。</p>\n<p>本期节目又名：《我们终于有了理由去浦东！》《Just 浦东，just 噗通》《抽屉原则在博物馆观展之应用》。</p>\n<h2>登场人物</h2>\n<p>婉莹：饿得快</p>\n<p>btr：抽屉原则研究员</p>\n<p>小施：热心市民，消息灵通</p>\n<h2>延伸链接</h2>\n<ul>\n<li><a href=\"https://www.clubhouse.com/event/myl44b9ehttps://www.clubhouse.com/event/myl44b9e\">八月十五号（明晚）的直播闲聊</a></li>\n<li><a href=\"https://podcasts.apple.com/cn/podcast/%E7%94%B3%E5%B1%95%E8%BF%90%E5%8A%A8-%E4%B8%8B-%E6%B5%A6%E4%B8%9C%E7%BE%8E%E6%9C%AF%E9%A6%86%E7%9A%84key-words-%E7%A2%97-%E9%87%8E%E5%BF%83-%E5%85%AC%E5%85%B1%E6%80%A7/id1493417568?i=1000529645615\">井户端会议</a></li>\n<li><a href=\"http://m.ximalaya.com/sound/431563018\">B 面电台</a></li>\n<li><a href=\"https://www.museumofartpd.org.cn/ticketing\">浦东美术馆购票入口</a></li>\n<li><a href=\"http://www.iarch.cn/thread-31877-1-1.html\">巴黎阿拉伯世界文化中心（Institute du Monde Arabe）让·努维尔</a></li>\n<li><a href=\"https://www.archdaily.cn/cn/914266/qia-ta-er-guo-jia-bo-wu-guan-rang-star-nu-wei-er-gong-zuo-shi\">卡塔尔国家博物馆 让·努维尔工作室</a></li>\n<li><a href=\"https://zh.wikipedia.org/wiki/%E8%87%B3%E4%B8%8A%E4%B8%BB%E4%B9%89\">至上主义</a></li>\n<li><a href=\"https://baike.baidu.com/item/%E5%B1%B1%E4%B8%9C%E7%99%BD%E9%BA%BB/8245157\">山东白麻石</a></li>\n<li><a href=\"http://www.rockbundartmuseum.org/cn/exhibition/overview/5d0fwz\">外滩美术馆第一展：农民达芬奇</a></li>\n<li><a href=\"https://book.douban.com/subject/30181685//\">《莫失莫忘》石黑一雄</a></li>\n<li><a href=\"https://book.douban.com/subject/30128189/\">《红发女人》帕慕克</a></li>\n<li><a href=\"https://artsandculture.google.com/asset/ophelia-sir-john-everett-millais/-wGU6cT4JixtPA\">谷歌艺术上的高清 Ophelia</a></li>\n</ul>\n<p>喜欢《博物志》，请考虑成为<a href=\"https://bowuzhi.fm/member\">会员</a>支持我们。</p>\n<p><a href=\"https://afdian.net/@bowuzhi\">《博物志》的爱发电页面</a></p>\n<p><a href=\"https://mianbaoduo.com/user/show/aWealms=\">单独购买往期通讯</a></p>\n<p><a href=\"https://weidian.com/?userid=1253336237&amp;p=iphone&amp;wfr=BuyercopyURL&amp;share_relation=a5eeac280c36c7c2__1\">购买周边请看这里</a></p>\n<p>Spotify：<a href=\"https://open.spotify.com/show/3keO8H1ymbuvV7qn36UmAg\">博物志</a></p>\n<p>Youtube 频道：<a href=\"https://www.youtube.com/feed/subscriptions/UC6mRJmp94jsa8megdfQLV4w\">博物志museelogue</a></p>\n<p>Bilibili 频道：<a href=\"https://space.bilibili.com/105185560?from=search&amp;seid=13635414942186953006\">博物志</a></p>\n<p><a href=\"https://live.bilibili.com/21528642?from=search&amp;seid=15255352836414836974\">Bilibili 直播间</a></p>\n<p>婉莹的个人<a href=\"https://t.me/bibiedit\">电报频道</a></p>\n<p>婉莹的个人<a href=\"https://www.youtube.com/channel/UCxlKo7y0lOIAGc0KF9HhAPA\">YouTube</a></p>\n<p>婉莹的个人<a href=\"https://space.bilibili.com/260972304/dynamic\">哔哩哔哩频道</a></p>\n<p><a href=\"https://mp.weixin.qq.com/mp/profile_ext?action=home&amp;__biz=MzU0Nzk3NDk5Ng==&amp;scene=124&amp;#wechat_redirect\">《哈利播客》公众号</a></p>\n<hr /><p><a href=\"https://afdian.net/@bowuzhi\" rel=\"payment\">爱发电上赞助</a></p>"
        }
    ],
    "published": "Sat, 14 Aug 2021 14:33:00 +0000",
    "published_parsed": [
        2021,
        8,
        14,
        14,
        33,
        0,
        5,
        226,
        0
    ]
}