{
    "title": "5. 编程字体",
    "title_detail": {
        "type": "text/plain",
        "language": null,
        "base": "https://pan.icu/feed",
        "value": "5. 编程字体"
    },
    "itunes_episode": "5",
    "itunes_title": "编程字体",
    "summary": "<p>从补遗上期未能提及的若干编辑器开始，follow up 持续了一小时，话题包括 .NET 跨平台、Handmade Hero、学徒工、DIN 1451 和 San Francisco 字体的差异。在后半部分，Rio 和吴涛分别历数了自己最喜欢的编程字体并分别做了推荐。</p>\n\n<h2>相关链接</h2>\n\n<ul>\n<li><a href=\"http://gameinfo.na.leagueoflegends.com/en/game-info/champions/vi/\">LoL 中的 Vi</a></li>\n<li><a href=\"http://programming.nu/\">Vico 所使用的 Nu 语言</a></li>\n<li><a href=\"http://www.macrabbit.com/espresso/\">MacRabbit Espresso</a></li>\n<li><a href=\"https://panic.com/coda/\">Coda</a></li>\n<li><a href=\"http://coteditor.com/\">支持竖排的 CotEditor</a></li>\n<li><a href=\"http://brackets.io/\">Bracket</a></li>\n<li><a href=\"http://www.jedit.org/\">jEdit</a></li>\n<li><a href=\"https://github.com/go-qml/qml\">QML 的 Go 语言 binding</a></li>\n<li><a href=\"http://quantum-os.github.io/\">Quantum OS</a></li>\n<li><a href=\"http://www.crimsoneditor.com/\">Crimson Editor</a></li>\n<li><a href=\"http://www.visualstudio.com/downloads/download-visual-studio-vs\">Visual Studio Community 2013 with Update 4</a></li>\n<li><a href=\"https://github.com/aspnet/home\">Github 上的 ASP.NET</a></li>\n<li><a href=\"http://handmadehero.org/\">Handmade Hero</a></li>\n<li><a href=\"http://www.twitch.tv/handmade_hero\">Handmade Hero 在 Twitch 上的频道</a></li>\n<li><a href=\"http://eclim.org/\">Eclim</a></li>\n<li><a href=\"http://www.pluralsight.com/\">Pluralsight，PeepCode 的后继网站</a></li>\n<li><a href=\"https://github.com/wellsriley/YosemiteSanFranciscoFont\">以 San Francisco Font 作为 Yosemite 系统字体</a></li>\n<li><a href=\"http://en.wikipedia.org/wiki/DIN_1451\">DIN 1451 字体</a></li>\n<li><a href=\"http://en.wikipedia.org/wiki/FE-Schrift\">德国车牌字体 FE-Schrift</a></li>\n<li><a href=\"https://en.wikipedia.org/wiki/San_Francisco_(1984_typeface)\">1984 年的 San Francisco 字体</a></li>\n<li><a href=\"http://en.wikipedia.org/wiki/Susan_Kare\">Susan Kare</a></li>\n<li><a href=\"http://en.wikipedia.org/wiki/Monaco_%28typeface%29\">Monaco 字体</a></li>\n<li><a href=\"http://en.wikipedia.org/wiki/Menlo_%28typeface%29\">Menlo 字体</a></li>\n<li><a href=\"http://input.fontbureau.com/info/\">Input 字体</a></li>\n<li><a href=\"http://en.wikipedia.org/wiki/Consolas\">Consolas 字体</a></li>\n<li><a href=\"http://store1.adobe.com/cfusion/store/html/index.cfm?event=displayFontPackage&amp;code=1960\">Source Code Pro 字体</a></li>\n<li><a href=\"http://www.google.com/fonts/specimen/PT+Mono\">PT Mono 字体</a></li>\n<li><a href=\"http://www.fsd.it/fonts/pragmatapro.htm\">PragmataPro 字体</a>、<a href=\"http://a.disquscdn.com/uploads/mediaembed/images/1463/5597/original.jpg\">其专为编程设计的 ligature</a></li>\n<li><a href=\"http://www.marksimonson.com/fonts/view/anonymous-pro\">Anonymous Pro</a></li>\n<li><a href=\"http://en.wikipedia.org/wiki/DejaVu_fonts#Sans_Mono\">DejaVu Sans Mono</a></li>\n<li><a href=\"http://www.linuxlibertine.org/index.php?id=2&amp;L=1\">Linux Libertine 系列字体</a></li>\n<li><a href=\"http://en.wikipedia.org/wiki/OCR-A_font\">OCR A</a></li>\n<li><a href=\"https://www.youtube.com/watch?v=ts_PVB5sR6U\">尚格云顿的沃尔沃广告片</a></li>\n<li><a href=\"https://www.youtube.com/watch?v=dndHQzZPH0Q\">针对上述广告的模仿版本之一</a>、<a href=\"https://www.youtube.com/watch?v=-9NE0BKE51g\">之二</a>、<a href=\"https://www.youtube.com/watch?v=JMSbrFLBz64\">之三</a></li>\n</ul>\n\n<h2>人物简介</h2>\n\n<ul>\n<li>Rio:《<a href=\"https://itgonglun.com\">IT 公论</a>》主播，<a href=\"https://ipn.li\">IPN</a> 联合创始人，<a href=\"https://apple4us.com\">Apple4us</a> 程序员。<br />\n</li>\n<li>吴涛：<a href=\"https://typeisbeautiful.com\">Type is Beautiful</a> 程序员，《内核恐慌》主播。</li>\n</ul>",
    "summary_detail": {
        "type": "text/html",
        "language": null,
        "base": "https://pan.icu/feed",
        "value": "<p>从补遗上期未能提及的若干编辑器开始，follow up 持续了一小时，话题包括 .NET 跨平台、Handmade Hero、学徒工、DIN 1451 和 San Francisco 字体的差异。在后半部分，Rio 和吴涛分别历数了自己最喜欢的编程字体并分别做了推荐。</p>\n\n<h2>相关链接</h2>\n\n<ul>\n<li><a href=\"http://gameinfo.na.leagueoflegends.com/en/game-info/champions/vi/\">LoL 中的 Vi</a></li>\n<li><a href=\"http://programming.nu/\">Vico 所使用的 Nu 语言</a></li>\n<li><a href=\"http://www.macrabbit.com/espresso/\">MacRabbit Espresso</a></li>\n<li><a href=\"https://panic.com/coda/\">Coda</a></li>\n<li><a href=\"http://coteditor.com/\">支持竖排的 CotEditor</a></li>\n<li><a href=\"http://brackets.io/\">Bracket</a></li>\n<li><a href=\"http://www.jedit.org/\">jEdit</a></li>\n<li><a href=\"https://github.com/go-qml/qml\">QML 的 Go 语言 binding</a></li>\n<li><a href=\"http://quantum-os.github.io/\">Quantum OS</a></li>\n<li><a href=\"http://www.crimsoneditor.com/\">Crimson Editor</a></li>\n<li><a href=\"http://www.visualstudio.com/downloads/download-visual-studio-vs\">Visual Studio Community 2013 with Update 4</a></li>\n<li><a href=\"https://github.com/aspnet/home\">Github 上的 ASP.NET</a></li>\n<li><a href=\"http://handmadehero.org/\">Handmade Hero</a></li>\n<li><a href=\"http://www.twitch.tv/handmade_hero\">Handmade Hero 在 Twitch 上的频道</a></li>\n<li><a href=\"http://eclim.org/\">Eclim</a></li>\n<li><a href=\"http://www.pluralsight.com/\">Pluralsight，PeepCode 的后继网站</a></li>\n<li><a href=\"https://github.com/wellsriley/YosemiteSanFranciscoFont\">以 San Francisco Font 作为 Yosemite 系统字体</a></li>\n<li><a href=\"http://en.wikipedia.org/wiki/DIN_1451\">DIN 1451 字体</a></li>\n<li><a href=\"http://en.wikipedia.org/wiki/FE-Schrift\">德国车牌字体 FE-Schrift</a></li>\n<li><a href=\"https://en.wikipedia.org/wiki/San_Francisco_(1984_typeface)\">1984 年的 San Francisco 字体</a></li>\n<li><a href=\"http://en.wikipedia.org/wiki/Susan_Kare\">Susan Kare</a></li>\n<li><a href=\"http://en.wikipedia.org/wiki/Monaco_%28typeface%29\">Monaco 字体</a></li>\n<li><a href=\"http://en.wikipedia.org/wiki/Menlo_%28typeface%29\">Menlo 字体</a></li>\n<li><a href=\"http://input.fontbureau.com/info/\">Input 字体</a></li>\n<li><a href=\"http://en.wikipedia.org/wiki/Consolas\">Consolas 字体</a></li>\n<li><a href=\"http://store1.adobe.com/cfusion/store/html/index.cfm?event=displayFontPackage&amp;code=1960\">Source Code Pro 字体</a></li>\n<li><a href=\"http://www.google.com/fonts/specimen/PT+Mono\">PT Mono 字体</a></li>\n<li><a href=\"http://www.fsd.it/fonts/pragmatapro.htm\">PragmataPro 字体</a>、<a href=\"http://a.disquscdn.com/uploads/mediaembed/images/1463/5597/original.jpg\">其专为编程设计的 ligature</a></li>\n<li><a href=\"http://www.marksimonson.com/fonts/view/anonymous-pro\">Anonymous Pro</a></li>\n<li><a href=\"http://en.wikipedia.org/wiki/DejaVu_fonts#Sans_Mono\">DejaVu Sans Mono</a></li>\n<li><a href=\"http://www.linuxlibertine.org/index.php?id=2&amp;L=1\">Linux Libertine 系列字体</a></li>\n<li><a href=\"http://en.wikipedia.org/wiki/OCR-A_font\">OCR A</a></li>\n<li><a href=\"https://www.youtube.com/watch?v=ts_PVB5sR6U\">尚格云顿的沃尔沃广告片</a></li>\n<li><a href=\"https://www.youtube.com/watch?v=dndHQzZPH0Q\">针对上述广告的模仿版本之一</a>、<a href=\"https://www.youtube.com/watch?v=-9NE0BKE51g\">之二</a>、<a href=\"https://www.youtube.com/watch?v=JMSbrFLBz64\">之三</a></li>\n</ul>\n\n<h2>人物简介</h2>\n\n<ul>\n<li>Rio:《<a href=\"https://itgonglun.com\">IT 公论</a>》主播，<a href=\"https://ipn.li\">IPN</a> 联合创始人，<a href=\"https://apple4us.com\">Apple4us</a> 程序员。<br />\n</li>\n<li>吴涛：<a href=\"https://typeisbeautiful.com\">Type is Beautiful</a> 程序员，《内核恐慌》主播。</li>\n</ul>"
    },
    "links": [
        {
            "rel": "alternate",
            "type": "text/html",
            "href": "https://pan.icu/5"
        },
        {
            "type": "audio/mpeg",
            "length": "100101750",
            "href": "https://pan.icu/5/audio.mp3",
            "rel": "enclosure"
        }
    ],
    "link": "https://pan.icu/5",
    "id": "https://pan.icu/5",
    "guidislink": false,
    "authors": [
        {
            "name": "吴涛、Rio"
        }
    ],
    "author": "吴涛、Rio",
    "author_detail": {
        "name": "吴涛、Rio"
    },
    "published": "Sun, 30 Nov 2014 01:31:03 +0000",
    "published_parsed": [
        2014,
        11,
        30,
        1,
        31,
        3,
        6,
        334,
        0
    ],
    "itunes_duration": "8331"
}