{
    "title": "131. “莫兰迪色”背后的莫兰迪",
    "title_detail": {
        "type": "text/plain",
        "language": null,
        "base": "https://feeds.fireside.fm/theviewtalk/rss",
        "value": "131. “莫兰迪色”背后的莫兰迪"
    },
    "links": [
        {
            "rel": "alternate",
            "type": "text/html",
            "href": "https://www.theviewtalk.com/131"
        },
        {
            "length": "48656438",
            "type": "audio/mpeg",
            "href": "https://aphid.fireside.fm/d/1437767933/271eaae7-5c3a-4a2c-aed6-39e245b9fb53/0cb6eb9a-1a24-4839-8575-c01e31a676b8.mp3",
            "rel": "enclosure"
        }
    ],
    "link": "https://www.theviewtalk.com/131",
    "id": "0cb6eb9a-1a24-4839-8575-c01e31a676b8",
    "guidislink": false,
    "published": "Sun, 14 Aug 2022 20:00:00 +0800",
    "published_parsed": [
        2022,
        8,
        14,
        12,
        0,
        0,
        6,
        226,
        0
    ],
    "authors": [
        {
            "name": "一画一话"
        },
        {
            "name": "一画一话"
        }
    ],
    "author": "一画一话",
    "author_detail": {
        "name": "一画一话"
    },
    "itunes_episodetype": "full",
    "subtitle": "",
    "subtitle_detail": {
        "type": "text/plain",
        "language": null,
        "base": "https://feeds.fireside.fm/theviewtalk/rss",
        "value": ""
    },
    "itunes_duration": "48:57",
    "itunes_explicit": null,
    "image": {
        "href": "https://assets.fireside.fm/file/fireside-images/podcasts/images/2/271eaae7-5c3a-4a2c-aed6-39e245b9fb53/episodes/0/0cb6eb9a-1a24-4839-8575-c01e31a676b8/cover.jpg"
    },
    "summary": "<p>「书话 02」，介绍一本特别的时尚影像刊物 SIXTEEN，欢迎在<a href=\"https://www.youtube.com/channel/UC0JlU5meb46IMV3vyXEi0ew\" rel=\"nofollow\">YouTube</a>，<a href=\"https://space.bilibili.com/521360088\" rel=\"nofollow\">bilibili</a>观看。</p>\n\n<p>时隔半年有余，主播再次走进美术馆。</p>\n\n<p>《乔治 莫兰迪》，久事美术馆“大师系列 ”特展的第三章，（前两展分别是蒙克，夏加尔）。<a href=\"https://www.theviewtalk.com/80\" rel=\"nofollow\">去年的蒙克展给主播们带来的是惊喜</a>，再去久事，看到了“莫兰迪色”背后的那个莫兰迪。</p>\n\n<p>莫兰迪鲜为人知的生平，只够艺术传播者拼凑出一个“隔绝尘世”安静画画的“僧侣”，但面对原作，“莫兰迪色”就像一个玩笑，马上退场，而一个试图压抑自己冲动的艺术家浮现在画面上。</p>\n\n<p>在中国美术教育上，莫兰迪也是举足轻重的存在，而通过画册教授给学生的莫兰迪，也可能是个误会。</p>\n\n<p>■ 主播<br />\n杨老师<br />\n躲在瓶瓶罐罐后面</p>\n\n<p>·</p>\n\n<p>■ Cover art 中作品<br />\nNatura morta（静物） / 乔治·莫兰迪 / 布面油画 / 1956 / 35 x 45 cm</p>\n\n<p>·</p>\n\n<p>■ Song List<br />\nna</p>\n\n<p>·</p>\n\n<p>■ 延伸内容<br />\nFarewell to Giorgio Morandi - Center for Italian Modern Art<br />\n<a href=\"https://www.italianmodernart.org/a-closer-look-at-giorgio-morandi/\" rel=\"nofollow\">https://www.italianmodernart.org/a-closer-look-at-giorgio-morandi/</a></p>\n\n<p>The 'Silent Perfection' of Artist Giorgio Morandi | Christie's<br />\n<a href=\"https://www.christies.com/features/Giorgio-Morandi-guide-10098-3.aspx\" rel=\"nofollow\">https://www.christies.com/features/Giorgio-Morandi-guide-10098-3.aspx</a></p>\n\n<p>·</p>\n\n<p>■ sns<br />\n感谢你的收听！关于节目和主播的动态，欢迎关注我们的社交号：<br />\n<a href=\"https://weibo.com/theviewtalk\" rel=\"nofollow\">「一画一话」微博</a><br />\n<a href=\"https://www.douban.com/people/theviewtalk/\" rel=\"nofollow\">「一画一话」豆瓣</a><br />\n<a href=\"https://www.instagram.com/theviewtalk/\" rel=\"nofollow\">Instagram上也可以找到我们。</a><br />\n如果你喜欢我们的节目请在你常用的平台留下好评，将节目分享给你的朋友。</p>\n\n<p>·</p>\n\n<p>■ 付费订阅<br />\n<a href=\"https://www.patreon.com/theviewtalk\" rel=\"nofollow\">patreon 订阅</a><br />\n<a href=\"https://afdian.net/@theviewtalk\" rel=\"nofollow\">爱发电 订阅</a></p>\n\n<p>·</p>\n\n<p>■ say hi<br />\n<a href=\"mailto:info@theviewtalk.com\" rel=\"nofollow\">info@theviewtalk.com</a></p>",
    "summary_detail": {
        "type": "text/html",
        "language": null,
        "base": "https://feeds.fireside.fm/theviewtalk/rss",
        "value": "<p>「书话 02」，介绍一本特别的时尚影像刊物 SIXTEEN，欢迎在<a href=\"https://www.youtube.com/channel/UC0JlU5meb46IMV3vyXEi0ew\" rel=\"nofollow\">YouTube</a>，<a href=\"https://space.bilibili.com/521360088\" rel=\"nofollow\">bilibili</a>观看。</p>\n\n<p>时隔半年有余，主播再次走进美术馆。</p>\n\n<p>《乔治 莫兰迪》，久事美术馆“大师系列 ”特展的第三章，（前两展分别是蒙克，夏加尔）。<a href=\"https://www.theviewtalk.com/80\" rel=\"nofollow\">去年的蒙克展给主播们带来的是惊喜</a>，再去久事，看到了“莫兰迪色”背后的那个莫兰迪。</p>\n\n<p>莫兰迪鲜为人知的生平，只够艺术传播者拼凑出一个“隔绝尘世”安静画画的“僧侣”，但面对原作，“莫兰迪色”就像一个玩笑，马上退场，而一个试图压抑自己冲动的艺术家浮现在画面上。</p>\n\n<p>在中国美术教育上，莫兰迪也是举足轻重的存在，而通过画册教授给学生的莫兰迪，也可能是个误会。</p>\n\n<p>■ 主播<br />\n杨老师<br />\n躲在瓶瓶罐罐后面</p>\n\n<p>·</p>\n\n<p>■ Cover art 中作品<br />\nNatura morta（静物） / 乔治·莫兰迪 / 布面油画 / 1956 / 35 x 45 cm</p>\n\n<p>·</p>\n\n<p>■ Song List<br />\nna</p>\n\n<p>·</p>\n\n<p>■ 延伸内容<br />\nFarewell to Giorgio Morandi - Center for Italian Modern Art<br />\n<a href=\"https://www.italianmodernart.org/a-closer-look-at-giorgio-morandi/\" rel=\"nofollow\">https://www.italianmodernart.org/a-closer-look-at-giorgio-morandi/</a></p>\n\n<p>The 'Silent Perfection' of Artist Giorgio Morandi | Christie's<br />\n<a href=\"https://www.christies.com/features/Giorgio-Morandi-guide-10098-3.aspx\" rel=\"nofollow\">https://www.christies.com/features/Giorgio-Morandi-guide-10098-3.aspx</a></p>\n\n<p>·</p>\n\n<p>■ sns<br />\n感谢你的收听！关于节目和主播的动态，欢迎关注我们的社交号：<br />\n<a href=\"https://weibo.com/theviewtalk\" rel=\"nofollow\">「一画一话」微博</a><br />\n<a href=\"https://www.douban.com/people/theviewtalk/\" rel=\"nofollow\">「一画一话」豆瓣</a><br />\n<a href=\"https://www.instagram.com/theviewtalk/\" rel=\"nofollow\">Instagram上也可以找到我们。</a><br />\n如果你喜欢我们的节目请在你常用的平台留下好评，将节目分享给你的朋友。</p>\n\n<p>·</p>\n\n<p>■ 付费订阅<br />\n<a href=\"https://www.patreon.com/theviewtalk\" rel=\"nofollow\">patreon 订阅</a><br />\n<a href=\"https://afdian.net/@theviewtalk\" rel=\"nofollow\">爱发电 订阅</a></p>\n\n<p>·</p>\n\n<p>■ say hi<br />\n<a href=\"mailto:info@theviewtalk.com\" rel=\"nofollow\">info@theviewtalk.com</a></p>"
    },
    "tags": [
        {
            "term": "莫兰迪",
            "scheme": "http://www.itunes.com/",
            "label": null
        },
        {
            "term": "意大利",
            "scheme": "http://www.itunes.com/",
            "label": null
        },
        {
            "term": "艺术",
            "scheme": "http://www.itunes.com/",
            "label": null
        },
        {
            "term": "绘画",
            "scheme": "http://www.itunes.com/",
            "label": null
        },
        {
            "term": "刘小东",
            "scheme": "http://www.itunes.com/",
            "label": null
        },
        {
            "term": "弗洛伊德",
            "scheme": "http://www.itunes.com/",
            "label": null
        },
        {
            "term": "美术教育",
            "scheme": "http://www.itunes.com/",
            "label": null
        },
        {
            "term": "古典",
            "scheme": "http://www.itunes.com/",
            "label": null
        },
        {
            "term": "原作",
            "scheme": "http://www.itunes.com/",
            "label": null
        }
    ],
    "content": [
        {
            "type": "text/html",
            "language": null,
            "base": "https://feeds.fireside.fm/theviewtalk/rss",
            "value": "<p>「书话 02」，介绍一本特别的时尚影像刊物 SIXTEEN，欢迎在<a href=\"https://www.youtube.com/channel/UC0JlU5meb46IMV3vyXEi0ew\" rel=\"nofollow\">YouTube</a>，<a href=\"https://space.bilibili.com/521360088\" rel=\"nofollow\">bilibili</a>观看。</p>\n\n<p>时隔半年有余，主播再次走进美术馆。</p>\n\n<p>《乔治 莫兰迪》，久事美术馆“大师系列 ”特展的第三章，（前两展分别是蒙克，夏加尔）。<a href=\"https://www.theviewtalk.com/80\" rel=\"nofollow\">去年的蒙克展给主播们带来的是惊喜</a>，再去久事，看到了“莫兰迪色”背后的那个莫兰迪。</p>\n\n<p>莫兰迪鲜为人知的生平，只够艺术传播者拼凑出一个“隔绝尘世”安静画画的“僧侣”，但面对原作，“莫兰迪色”就像一个玩笑，马上退场，而一个试图压抑自己冲动的艺术家浮现在画面上。</p>\n\n<p>在中国美术教育上，莫兰迪也是举足轻重的存在，而通过画册教授给学生的莫兰迪，也可能是个误会。</p>\n\n<p>■ 主播<br />\n杨老师<br />\n躲在瓶瓶罐罐后面</p>\n\n<p>·</p>\n\n<p>■ Cover art 中作品<br />\nNatura morta（静物） / 乔治·莫兰迪 / 布面油画 / 1956 / 35 x 45 cm</p>\n\n<p>·</p>\n\n<p>■ Song List<br />\nna</p>\n\n<p>·</p>\n\n<p>■ 延伸内容<br />\nFarewell to Giorgio Morandi - Center for Italian Modern Art<br />\n<a href=\"https://www.italianmodernart.org/a-closer-look-at-giorgio-morandi/\" rel=\"nofollow\">https://www.italianmodernart.org/a-closer-look-at-giorgio-morandi/</a></p>\n\n<p>The 'Silent Perfection' of Artist Giorgio Morandi | Christie's<br />\n<a href=\"https://www.christies.com/features/Giorgio-Morandi-guide-10098-3.aspx\" rel=\"nofollow\">https://www.christies.com/features/Giorgio-Morandi-guide-10098-3.aspx</a></p>\n\n<p>·</p>\n\n<p>■ sns<br />\n感谢你的收听！关于节目和主播的动态，欢迎关注我们的社交号：<br />\n<a href=\"https://weibo.com/theviewtalk\" rel=\"nofollow\">「一画一话」微博</a><br />\n<a href=\"https://www.douban.com/people/theviewtalk/\" rel=\"nofollow\">「一画一话」豆瓣</a><br />\n<a href=\"https://www.instagram.com/theviewtalk/\" rel=\"nofollow\">Instagram上也可以找到我们。</a><br />\n如果你喜欢我们的节目请在你常用的平台留下好评，将节目分享给你的朋友。</p>\n\n<p>·</p>\n\n<p>■ 付费订阅<br />\n<a href=\"https://www.patreon.com/theviewtalk\" rel=\"nofollow\">patreon 订阅</a><br />\n<a href=\"https://afdian.net/@theviewtalk\" rel=\"nofollow\">爱发电 订阅</a></p>\n\n<p>·</p>\n\n<p>■ say hi<br />\n<a href=\"mailto:info@theviewtalk.com\" rel=\"nofollow\">info@theviewtalk.com</a></p>"
        }
    ],
    "fireside_playerurl": "https://fireside.fm/player/v2/yS2zkE2S+BEZEkYeq",
    "fireside_playerembedcode": "<iframe src=\"https://fireside.fm/player/v2/yS2zkE2S+BEZEkYeq\" width=\"740\" height=\"200\" frameborder=\"0\" scrolling=\"no\">",
    "podcast_person": {
        "email": "",
        "href": "",
        "role": "host"
    }
}