{
    "title": "56 「沃尔夫冈·提尔曼斯」交流会",
    "title_detail": {
        "type": "text/plain",
        "language": null,
        "base": "https://feeds.fireside.fm/arbretalk/rss",
        "value": "56 「沃尔夫冈·提尔曼斯」交流会"
    },
    "links": [
        {
            "rel": "alternate",
            "type": "text/html",
            "href": "https://www.arbretalk.com/56"
        },
        {
            "length": "71037754",
            "type": "audio/mpeg",
            "href": "https://aphid.fireside.fm/d/1437767933/8ecd4d04-d9eb-48ed-bafc-9ab55e67c940/5b468027-41de-4634-97ac-6659bc4d126c.mp3",
            "rel": "enclosure"
        }
    ],
    "link": "https://www.arbretalk.com/56",
    "id": "5b468027-41de-4634-97ac-6659bc4d126c",
    "guidislink": false,
    "published": "Tue, 14 Jun 2022 17:00:00 +0800",
    "published_parsed": [
        2022,
        6,
        14,
        9,
        0,
        0,
        1,
        165,
        0
    ],
    "authors": [
        {
            "name": "一树Arbre"
        },
        {
            "name": "一树Arbre"
        }
    ],
    "author": "一树Arbre",
    "author_detail": {
        "name": "一树Arbre"
    },
    "itunes_episodetype": "full",
    "subtitle": "由三名不知名摄影师主持的艺术跑题闲聊节目",
    "subtitle_detail": {
        "type": "text/plain",
        "language": null,
        "base": "https://feeds.fireside.fm/arbretalk/rss",
        "value": "由三名不知名摄影师主持的艺术跑题闲聊节目"
    },
    "itunes_duration": "1:13:54",
    "itunes_explicit": null,
    "summary": "<p>「艺术家系列」2021年份终于收尾了。<br />\n这一次和<a href=\"https://www.xiaoyuzhoufm.com/podcast/5e7c7849418a84a046ab2f53\" rel=\"nofollow\">《阿米小酒馆》</a>的米同学一起聊沃尔夫冈·提尔曼斯（Wolfgang Tillmans），同时还有三位现场听众的即时反馈。</p>\n\n<p>嘉宾：米同学<br />\n主播：Lavi，Shane，Val<br />\n听众：听众1，曹象，阿毛</p>\n\n<p><strong>章节提要</strong>：<br />\n00:00:29 嘉宾介绍<br />\n00:01:00 Val的选择理由<br />\n00:01:35 大家的第一印象<br />\n00:07:00 特殊的展览呈现方式<br />\n00:24:56 出版物的编排方式<br />\n00:26:18 Tillmans的创作轨迹<br />\n00:28:47 Tillmans的目光<br />\n00:30:34 对照1：Thomas Demand<br />\n00:33:28 「垂危物」<br />\n00:37:26 Tillmans的抽象作品<br />\n00:40:55 摄影学习的阶段<br />\n00:47:01 多才多艺<br />\n00:48:44 Tillmans作品的现时性和永恒性<br />\n00:52:36 对照2：川内伦子<br />\n00:53:38 一直站在鸡蛋的一边<br />\n00:54:34 现场观众1：《Wako6》<br />\n01:01:04 现场观众2：与绘画的关系<br />\n01:03:42 固化的手法和新的范式<br />\n01:08:38 作品和展览取名<br />\n01:11:29 Tillmans目光是脆弱的<br />\n01:12:23 END</p>\n\n<p><strong>相关链接</strong>：</p>\n\n<ol>\n<li>Wolfgang Tillmans的<a href=\"https://tillmans.co.uk/\" rel=\"nofollow\">网站</a></li>\n<li>听歌可去Wolfgang Tillmans的<a href=\"https://soundcloud.com/fragilelabel\" rel=\"nofollow\">SoundCloud</a> </li>\n<li>New Yorker的专题文章<a href=\"https://www.newyorker.com/magazine/2018/09/10/the-life-and-art-of-wolfgang-tillmans\" rel=\"nofollow\">《The Life and Art of Wolfgang Tillmans》</a></li>\n<li>米同学的文章<a href=\"https://mp.weixin.qq.com/s/eor9241u0U0eM-ade3E4ow\" rel=\"nofollow\">《再谈沃尔夫冈•提尔曼斯的作品悬挂方法》</a></li>\n<li>「垂危物」来自哈尔·福斯特<a href=\"https://book.douban.com/subject/35143710/\" rel=\"nofollow\">《来日非善》</a></li>\n</ol>\n\n<p><strong>音乐</strong>：Rofeu-Rays of gold</p><p>Special Guests: 米同学 and 阿毛.</p>",
    "summary_detail": {
        "type": "text/html",
        "language": null,
        "base": "https://feeds.fireside.fm/arbretalk/rss",
        "value": "<p>「艺术家系列」2021年份终于收尾了。<br />\n这一次和<a href=\"https://www.xiaoyuzhoufm.com/podcast/5e7c7849418a84a046ab2f53\" rel=\"nofollow\">《阿米小酒馆》</a>的米同学一起聊沃尔夫冈·提尔曼斯（Wolfgang Tillmans），同时还有三位现场听众的即时反馈。</p>\n\n<p>嘉宾：米同学<br />\n主播：Lavi，Shane，Val<br />\n听众：听众1，曹象，阿毛</p>\n\n<p><strong>章节提要</strong>：<br />\n00:00:29 嘉宾介绍<br />\n00:01:00 Val的选择理由<br />\n00:01:35 大家的第一印象<br />\n00:07:00 特殊的展览呈现方式<br />\n00:24:56 出版物的编排方式<br />\n00:26:18 Tillmans的创作轨迹<br />\n00:28:47 Tillmans的目光<br />\n00:30:34 对照1：Thomas Demand<br />\n00:33:28 「垂危物」<br />\n00:37:26 Tillmans的抽象作品<br />\n00:40:55 摄影学习的阶段<br />\n00:47:01 多才多艺<br />\n00:48:44 Tillmans作品的现时性和永恒性<br />\n00:52:36 对照2：川内伦子<br />\n00:53:38 一直站在鸡蛋的一边<br />\n00:54:34 现场观众1：《Wako6》<br />\n01:01:04 现场观众2：与绘画的关系<br />\n01:03:42 固化的手法和新的范式<br />\n01:08:38 作品和展览取名<br />\n01:11:29 Tillmans目光是脆弱的<br />\n01:12:23 END</p>\n\n<p><strong>相关链接</strong>：</p>\n\n<ol>\n<li>Wolfgang Tillmans的<a href=\"https://tillmans.co.uk/\" rel=\"nofollow\">网站</a></li>\n<li>听歌可去Wolfgang Tillmans的<a href=\"https://soundcloud.com/fragilelabel\" rel=\"nofollow\">SoundCloud</a> </li>\n<li>New Yorker的专题文章<a href=\"https://www.newyorker.com/magazine/2018/09/10/the-life-and-art-of-wolfgang-tillmans\" rel=\"nofollow\">《The Life and Art of Wolfgang Tillmans》</a></li>\n<li>米同学的文章<a href=\"https://mp.weixin.qq.com/s/eor9241u0U0eM-ade3E4ow\" rel=\"nofollow\">《再谈沃尔夫冈•提尔曼斯的作品悬挂方法》</a></li>\n<li>「垂危物」来自哈尔·福斯特<a href=\"https://book.douban.com/subject/35143710/\" rel=\"nofollow\">《来日非善》</a></li>\n</ol>\n\n<p><strong>音乐</strong>：Rofeu-Rays of gold</p><p>Special Guests: 米同学 and 阿毛.</p>"
    },
    "tags": [
        {
            "term": "摄影，艺术，文化，",
            "scheme": "http://www.itunes.com/",
            "label": null
        }
    ],
    "content": [
        {
            "type": "text/html",
            "language": null,
            "base": "https://feeds.fireside.fm/arbretalk/rss",
            "value": "<p>「艺术家系列」2021年份终于收尾了。<br />\n这一次和<a href=\"https://www.xiaoyuzhoufm.com/podcast/5e7c7849418a84a046ab2f53\" rel=\"nofollow\">《阿米小酒馆》</a>的米同学一起聊沃尔夫冈·提尔曼斯（Wolfgang Tillmans），同时还有三位现场听众的即时反馈。</p>\n\n<p>嘉宾：米同学<br />\n主播：Lavi，Shane，Val<br />\n听众：听众1，曹象，阿毛</p>\n\n<p><strong>章节提要</strong>：<br />\n00:00:29 嘉宾介绍<br />\n00:01:00 Val的选择理由<br />\n00:01:35 大家的第一印象<br />\n00:07:00 特殊的展览呈现方式<br />\n00:24:56 出版物的编排方式<br />\n00:26:18 Tillmans的创作轨迹<br />\n00:28:47 Tillmans的目光<br />\n00:30:34 对照1：Thomas Demand<br />\n00:33:28 「垂危物」<br />\n00:37:26 Tillmans的抽象作品<br />\n00:40:55 摄影学习的阶段<br />\n00:47:01 多才多艺<br />\n00:48:44 Tillmans作品的现时性和永恒性<br />\n00:52:36 对照2：川内伦子<br />\n00:53:38 一直站在鸡蛋的一边<br />\n00:54:34 现场观众1：《Wako6》<br />\n01:01:04 现场观众2：与绘画的关系<br />\n01:03:42 固化的手法和新的范式<br />\n01:08:38 作品和展览取名<br />\n01:11:29 Tillmans目光是脆弱的<br />\n01:12:23 END</p>\n\n<p><strong>相关链接</strong>：</p>\n\n<ol>\n<li>Wolfgang Tillmans的<a href=\"https://tillmans.co.uk/\" rel=\"nofollow\">网站</a></li>\n<li>听歌可去Wolfgang Tillmans的<a href=\"https://soundcloud.com/fragilelabel\" rel=\"nofollow\">SoundCloud</a> </li>\n<li>New Yorker的专题文章<a href=\"https://www.newyorker.com/magazine/2018/09/10/the-life-and-art-of-wolfgang-tillmans\" rel=\"nofollow\">《The Life and Art of Wolfgang Tillmans》</a></li>\n<li>米同学的文章<a href=\"https://mp.weixin.qq.com/s/eor9241u0U0eM-ade3E4ow\" rel=\"nofollow\">《再谈沃尔夫冈•提尔曼斯的作品悬挂方法》</a></li>\n<li>「垂危物」来自哈尔·福斯特<a href=\"https://book.douban.com/subject/35143710/\" rel=\"nofollow\">《来日非善》</a></li>\n</ol>\n\n<p><strong>音乐</strong>：Rofeu-Rays of gold</p><p>Special Guests: 米同学 and 阿毛.</p>"
        }
    ],
    "fireside_playerurl": "https://fireside.fm/player/v2/RF2PpSZw+fv-Wenpj",
    "fireside_playerembedcode": "<iframe src=\"https://fireside.fm/player/v2/RF2PpSZw+fv-Wenpj\" width=\"740\" height=\"200\" frameborder=\"0\" scrolling=\"no\">",
    "podcast_person": {
        "email": "",
        "href": "",
        "role": "guest"
    }
}